CHANGELOG
LICENSE
MANIFEST.in
README.rst
easymoney.py
setup.py
django_easymoney.egg-info/PKG-INFO
django_easymoney.egg-info/SOURCES.txt
django_easymoney.egg-info/dependency_links.txt
django_easymoney.egg-info/pbr.json
django_easymoney.egg-info/requires.txt
django_easymoney.egg-info/top_level.txt